[
  {
    "Inputs": [
      {
        "InputType": 0,
        "InputData": {
          "Values": [
            -0.03530108,
            0.221889138,
            0.09811865
          ],
          "DataType": 3
        }
      },
      {
        "InputType": 0,
        "InputData": {
          "Values": [
            0.0215187836,
            0.07374948,
            -0.129604191
          ],
          "DataType": 3
        }
      }
    ],
    "Outputs": [
      {
        "OutputType": 0,
        "OutputData": {
          "Values": [
            0.0
          ],
          "DataType": 0
        }
      }
    ]
  },
  {
    "Inputs": [
      {
        "InputType": 0,
        "InputData": {
          "Values": [
            -0.03577347,
            0.226062655,
            0.09977293
          ],
          "DataType": 3
        }
      },
      {
        "InputType": 0,
        "InputData": {
          "Values": [
            0.0355406478,
            0.111119218,
            -0.117262423
          ],
          "DataType": 3
        }
      }
    ],
    "Outputs": [
      {
        "OutputType": 0,
        "OutputData": {
          "Values": [
            0.0
          ],
          "DataType": 0
        }
      }
    ]
  },
  {
    "Inputs": [
      {
        "InputType": 0,
        "InputData": {
          "Values": [
            -0.0379852057,
            0.235914811,
            0.100511059
          ],
          "DataType": 3
        }
      },
      {
        "InputType": 0,
        "InputData": {
          "Values": [
            0.0188480522,
            0.196108386,
            -0.110975392
          ],
          "DataType": 3
        }
      }
    ],
    "Outputs": [
      {
        "OutputType": 0,
        "OutputData": {
          "Values": [
            0.0
          ],
          "DataType": 0
        }
      }
    ]
  },
  {
    "Inputs": [
      {
        "InputType": 0,
        "InputData": {
          "Values": [
            -0.0403633751,
            0.250982672,
            0.09561356
          ],
          "DataType": 3
        }
      },
      {
        "InputType": 0,
        "InputData": {
          "Values": [
            -0.0067531364,
            0.264980942,
            -0.103567556
          ],
          "DataType": 3
        }
      }
    ],
    "Outputs": [
      {
        "OutputType": 0,
        "OutputData": {
          "Values": [
            0.0
          ],
          "DataType": 0
        }
      }
    ]
  },
  {
    "Inputs": [
      {
        "InputType": 0,
        "InputData": {
          "Values": [
            -0.0417121649,
            0.26272738,
            0.09273097
          ],
          "DataType": 3
        }
      },
      {
        "InputType": 0,
        "InputData": {
          "Values": [
            -0.0142799681,
            0.279329836,
            -0.1051067
          ],
          "DataType": 3
        }
      }
    ],
    "Outputs": [
      {
        "OutputType": 0,
        "OutputData": {
          "Values": [
            0.0
          ],
          "DataType": 0
        }
      }
    ]
  },
  {
    "Inputs": [
      {
        "InputType": 0,
        "InputData": {
          "Values": [
            -0.0395741351,
            0.2647199,
            0.09160742
          ],
          "DataType": 3
        }
      },
      {
        "InputType": 0,
        "InputData": {
          "Values": [
            -0.0120803174,
            0.2715395,
            -0.110476606
          ],
          "DataType": 3
        }
      }
    ],
    "Outputs": [
      {
        "OutputType": 0,
        "OutputData": {
          "Values": [
            0.0
          ],
          "DataType": 0
        }
      }
    ]
  },
  {
    "Inputs": [
      {
        "InputType": 0,
        "InputData": {
          "Values": [
            -0.0392957553,
            0.265661657,
            0.09214469
          ],
          "DataType": 3
        }
      },
      {
        "InputType": 0,
        "InputData": {
          "Values": [
            -0.0107010454,
            0.266153753,
            -0.112007342
          ],
          "DataType": 3
        }
      }
    ],
    "Outputs": [
      {
        "OutputType": 0,
        "OutputData": {
          "Values": [
            0.0
          ],
          "DataType": 0
        }
      }
    ]
  },
  {
    "Inputs": [
      {
        "InputType": 0,
        "InputData": {
          "Values": [
            -0.03912723,
            0.263398737,
            0.09223616
          ],
          "DataType": 3
        }
      },
      {
        "InputType": 0,
        "InputData": {
          "Values": [
            -0.009794791,
            0.261748552,
            -0.112958983
          ],
          "DataType": 3
        }
      }
    ],
    "Outputs": [
      {
        "OutputType": 0,
        "OutputData": {
          "Values": [
            0.0
          ],
          "DataType": 0
        }
      }
    ]
  },
  {
    "Inputs": [
      {
        "InputType": 0,
        "InputData": {
          "Values": [
            -0.0395315364,
            0.263136476,
            0.09217672
          ],
          "DataType": 3
        }
      },
      {
        "InputType": 0,
        "InputData": {
          "Values": [
            -0.009437855,
            0.266174763,
            -0.114133365
          ],
          "DataType": 3
        }
      }
    ],
    "Outputs": [
      {
        "OutputType": 0,
        "OutputData": {
          "Values": [
            0.0
          ],
          "DataType": 0
        }
      }
    ]
  },
  {
    "Inputs": [
      {
        "InputType": 0,
        "InputData": {
          "Values": [
            -0.03984857,
            0.262826264,
            0.09194644
          ],
          "DataType": 3
        }
      },
      {
        "InputType": 0,
        "InputData": {
          "Values": [
            -0.009200115,
            0.267469436,
            -0.114081338
          ],
          "DataType": 3
        }
      }
    ],
    "Outputs": [
      {
        "OutputType": 0,
        "OutputData": {
          "Values": [
            0.0
          ],
          "DataType": 0
        }
      }
    ]
  },
  {
    "Inputs": [
      {
        "InputType": 0,
        "InputData": {
          "Values": [
            -0.0401588455,
            0.261777878,
            0.0922194943
          ],
          "DataType": 3
        }
      },
      {
        "InputType": 0,
        "InputData": {
          "Values": [
            -0.0102014095,
            0.266666561,
            -0.11315719
          ],
          "DataType": 3
        }
      }
    ],
    "Outputs": [
      {
        "OutputType": 0,
        "OutputData": {
          "Values": [
            0.0
          ],
          "DataType": 0
        }
      }
    ]
  },
  {
    "Inputs": [
      {
        "InputType": 0,
        "InputData": {
          "Values": [
            -0.0395820551,
            0.259637117,
            0.0929387659
          ],
          "DataType": 3
        }
      },
      {
        "InputType": 0,
        "InputData": {
          "Values": [
            -0.0109694116,
            0.2622195,
            -0.111029677
          ],
          "DataType": 3
        }
      }
    ],
    "Outputs": [
      {
        "OutputType": 0,
        "OutputData": {
          "Values": [
            0.0
          ],
          "DataType": 0
        }
      }
    ]
  },
  {
    "Inputs": [
      {
        "InputType": 0,
        "InputData": {
          "Values": [
            -0.0382639,
            0.258222222,
            0.0940542743
          ],
          "DataType": 3
        }
      },
      {
        "InputType": 0,
        "InputData": {
          "Values": [
            -0.01236376,
            0.258603126,
            -0.104466118
          ],
          "DataType": 3
        }
      }
    ],
    "Outputs": [
      {
        "OutputType": 0,
        "OutputData": {
          "Values": [
            0.0
          ],
          "DataType": 0
        }
      }
    ]
  },
  {
    "Inputs": [
      {
        "InputType": 0,
        "InputData": {
          "Values": [
            -0.03821035,
            0.25986135,
            0.0949198157
          ],
          "DataType": 3
        }
      },
      {
        "InputType": 0,
        "InputData": {
          "Values": [
            -0.0114959255,
            0.261522919,
            -0.101215318
          ],
          "DataType": 3
        }
      }
    ],
    "Outputs": [
      {
        "OutputType": 0,
        "OutputData": {
          "Values": [
            0.0
          ],
          "DataType": 0
        }
      }
    ]
  },
  {
    "Inputs": [
      {
        "InputType": 0,
        "InputData": {
          "Values": [
            -0.03749373,
            0.257000566,
            0.0955719948
          ],
          "DataType": 3
        }
      },
      {
        "InputType": 0,
        "InputData": {
          "Values": [
            -0.01028886,
            0.260860056,
            -0.101543665
          ],
          "DataType": 3
        }
      }
    ],
    "Outputs": [
      {
        "OutputType": 0,
        "OutputData": {
          "Values": [
            0.0
          ],
          "DataType": 0
        }
      }
    ]
  },
  {
    "Inputs": [
      {
        "InputType": 0,
        "InputData": {
          "Values": [
            -0.0370304063,
            0.256572545,
            0.0961944461
          ],
          "DataType": 3
        }
      },
      {
        "InputType": 0,
        "InputData": {
          "Values": [
            -0.00952982,
            0.2626326,
            -0.101952739
          ],
          "DataType": 3
        }
      }
    ],
    "Outputs": [
      {
        "OutputType": 0,
        "OutputData": {
          "Values": [
            0.0
          ],
          "DataType": 0
        }
      }
    ]
  },
  {
    "Inputs": [
      {
        "InputType": 0,
        "InputData": {
          "Values": [
            -0.0359966159,
            0.2561269,
            0.09671524
          ],
          "DataType": 3
        }
      },
      {
        "InputType": 0,
        "InputData": {
          "Values": [
            -0.008193053,
            0.261916637,
            -0.101389863
          ],
          "DataType": 3
        }
      }
    ],
    "Outputs": [
      {
        "OutputType": 0,
        "OutputData": {
          "Values": [
            0.0
          ],
          "DataType": 0
        }
      }
    ]
  },
  {
    "Inputs": [
      {
        "InputType": 0,
        "InputData": {
          "Values": [
            -0.0355460458,
            0.255301148,
            0.09660867
          ],
          "DataType": 3
        }
      },
      {
        "InputType": 0,
        "InputData": {
          "Values": [
            -0.00727000972,
            0.259997874,
            -0.101878263
          ],
          "DataType": 3
        }
      }
    ],
    "Outputs": [
      {
        "OutputType": 0,
        "OutputData": {
          "Values": [
            0.0
          ],
          "DataType": 0
        }
      }
    ]
  },
  {
    "Inputs": [
      {
        "InputType": 0,
        "InputData": {
          "Values": [
            -0.0349078961,
            0.253421962,
            0.09600499
          ],
          "DataType": 3
        }
      },
      {
        "InputType": 0,
        "InputData": {
          "Values": [
            -0.005459279,
            0.2599739,
            -0.1036282
          ],
          "DataType": 3
        }
      }
    ],
    "Outputs": [
      {
        "OutputType": 0,
        "OutputData": {
          "Values": [
            0.0
          ],
          "DataType": 0
        }
      }
    ]
  },
  {
    "Inputs": [
      {
        "InputType": 0,
        "InputData": {
          "Values": [
            -0.0341851674,
            0.24891381,
            0.09675687
          ],
          "DataType": 3
        }
      },
      {
        "InputType": 0,
        "InputData": {
          "Values": [
            0.012142159,
            0.223811135,
            -0.111303382
          ],
          "DataType": 3
        }
      }
    ],
    "Outputs": [
      {
        "OutputType": 0,
        "OutputData": {
          "Values": [
            0.0
          ],
          "DataType": 0
        }
      }
    ]
  },
  {
    "Inputs": [
      {
        "InputType": 0,
        "InputData": {
          "Values": [
            -0.0350437872,
            0.239514112,
            0.09695116
          ],
          "DataType": 3
        }
      },
      {
        "InputType": 0,
        "InputData": {
          "Values": [
            0.0330586545,
            0.123143882,
            -0.116758704
          ],
          "DataType": 3
        }
      }
    ],
    "Outputs": [
      {
        "OutputType": 0,
        "OutputData": {
          "Values": [
            0.0
          ],
          "DataType": 0
        }
      }
    ]
  },
  {
    "Inputs": [
      {
        "InputType": 0,
        "InputData": {
          "Values": [
            -0.03804833,
            0.232797772,
            0.09758748
          ],
          "DataType": 3
        }
      },
      {
        "InputType": 0,
        "InputData": {
          "Values": [
            0.0331017151,
            0.08294115,
            -0.1136038
          ],
          "DataType": 3
        }
      }
    ],
    "Outputs": [
      {
        "OutputType": 0,
        "OutputData": {
          "Values": [
            0.0
          ],
          "DataType": 0
        }
      }
    ]
  },
  {
    "Inputs": [
      {
        "InputType": 0,
        "InputData": {
          "Values": [
            -0.0717325658,
            0.128061861,
            0.161757544
          ],
          "DataType": 3
        }
      },
      {
        "InputType": 0,
        "InputData": {
          "Values": [
            0.0190913882,
            0.0718936,
            -0.1944698
          ],
          "DataType": 3
        }
      }
    ],
    "Outputs": [
      {
        "OutputType": 0,
        "OutputData": {
          "Values": [
            2.0
          ],
          "DataType": 0
        }
      }
    ]
  },
  {
    "Inputs": [
      {
        "InputType": 0,
        "InputData": {
          "Values": [
            -0.0717325658,
            0.128061861,
            0.161757544
          ],
          "DataType": 3
        }
      },
      {
        "InputType": 0,
        "InputData": {
          "Values": [
            0.0190913882,
            0.0718936,
            -0.1944698
          ],
          "DataType": 3
        }
      }
    ],
    "Outputs": [
      {
        "OutputType": 0,
        "OutputData": {
          "Values": [
            2.0
          ],
          "DataType": 0
        }
      }
    ]
  },
  {
    "Inputs": [
      {
        "InputType": 0,
        "InputData": {
          "Values": [
            -0.0717325658,
            0.128061861,
            0.161757544
          ],
          "DataType": 3
        }
      },
      {
        "InputType": 0,
        "InputData": {
          "Values": [
            0.0190913882,
            0.0718936,
            -0.1944698
          ],
          "DataType": 3
        }
      }
    ],
    "Outputs": [
      {
        "OutputType": 0,
        "OutputData": {
          "Values": [
            2.0
          ],
          "DataType": 0
        }
      }
    ]
  },
  {
    "Inputs": [
      {
        "InputType": 0,
        "InputData": {
          "Values": [
            -0.0717325658,
            0.128061861,
            0.161757544
          ],
          "DataType": 3
        }
      },
      {
        "InputType": 0,
        "InputData": {
          "Values": [
            0.0190913882,
            0.0718936,
            -0.1944698
          ],
          "DataType": 3
        }
      }
    ],
    "Outputs": [
      {
        "OutputType": 0,
        "OutputData": {
          "Values": [
            2.0
          ],
          "DataType": 0
        }
      }
    ]
  },
  {
    "Inputs": [
      {
        "InputType": 0,
        "InputData": {
          "Values": [
            -0.0717325658,
            0.128061861,
            0.161757544
          ],
          "DataType": 3
        }
      },
      {
        "InputType": 0,
        "InputData": {
          "Values": [
            0.0190913882,
            0.0718936,
            -0.1944698
          ],
          "DataType": 3
        }
      }
    ],
    "Outputs": [
      {
        "OutputType": 0,
        "OutputData": {
          "Values": [
            2.0
          ],
          "DataType": 0
        }
      }
    ]
  },
  {
    "Inputs": [
      {
        "InputType": 0,
        "InputData": {
          "Values": [
            -0.0717325658,
            0.128061861,
            0.161757544
          ],
          "DataType": 3
        }
      },
      {
        "InputType": 0,
        "InputData": {
          "Values": [
            0.0190913882,
            0.0718936,
            -0.1944698
          ],
          "DataType": 3
        }
      }
    ],
    "Outputs": [
      {
        "OutputType": 0,
        "OutputData": {
          "Values": [
            2.0
          ],
          "DataType": 0
        }
      }
    ]
  },
  {
    "Inputs": [
      {
        "InputType": 0,
        "InputData": {
          "Values": [
            -0.0717325658,
            0.128061861,
            0.161757544
          ],
          "DataType": 3
        }
      },
      {
        "InputType": 0,
        "InputData": {
          "Values": [
            0.0190913882,
            0.0718936,
            -0.1944698
          ],
          "DataType": 3
        }
      }
    ],
    "Outputs": [
      {
        "OutputType": 0,
        "OutputData": {
          "Values": [
            2.0
          ],
          "DataType": 0
        }
      }
    ]
  },
  {
    "Inputs": [
      {
        "InputType": 0,
        "InputData": {
          "Values": [
            -0.0717325658,
            0.128061861,
            0.161757544
          ],
          "DataType": 3
        }
      },
      {
        "InputType": 0,
        "InputData": {
          "Values": [
            0.0190913882,
            0.0718936,
            -0.1944698
          ],
          "DataType": 3
        }
      }
    ],
    "Outputs": [
      {
        "OutputType": 0,
        "OutputData": {
          "Values": [
            2.0
          ],
          "DataType": 0
        }
      }
    ]
  },
  {
    "Inputs": [
      {
        "InputType": 0,
        "InputData": {
          "Values": [
            -0.0717325658,
            0.128061861,
            0.161757544
          ],
          "DataType": 3
        }
      },
      {
        "InputType": 0,
        "InputData": {
          "Values": [
            0.0190913882,
            0.0718936,
            -0.1944698
          ],
          "DataType": 3
        }
      }
    ],
    "Outputs": [
      {
        "OutputType": 0,
        "OutputData": {
          "Values": [
            2.0
          ],
          "DataType": 0
        }
      }
    ]
  },
  {
    "Inputs": [
      {
        "InputType": 0,
        "InputData": {
          "Values": [
            -0.0717325658,
            0.128061861,
            0.161757544
          ],
          "DataType": 3
        }
      },
      {
        "InputType": 0,
        "InputData": {
          "Values": [
            0.0190913882,
            0.0718936,
            -0.1944698
          ],
          "DataType": 3
        }
      }
    ],
    "Outputs": [
      {
        "OutputType": 0,
        "OutputData": {
          "Values": [
            2.0
          ],
          "DataType": 0
        }
      }
    ]
  },
  {
    "Inputs": [
      {
        "InputType": 0,
        "InputData": {
          "Values": [
            -0.0717325658,
            0.128061861,
            0.161757544
          ],
          "DataType": 3
        }
      },
      {
        "InputType": 0,
        "InputData": {
          "Values": [
            0.0190913882,
            0.0718936,
            -0.1944698
          ],
          "DataType": 3
        }
      }
    ],
    "Outputs": [
      {
        "OutputType": 0,
        "OutputData": {
          "Values": [
            2.0
          ],
          "DataType": 0
        }
      }
    ]
  },
  {
    "Inputs": [
      {
        "InputType": 0,
        "InputData": {
          "Values": [
            -0.0717325658,
            0.128061861,
            0.161757544
          ],
          "DataType": 3
        }
      },
      {
        "InputType": 0,
        "InputData": {
          "Values": [
            0.0159901772,
            0.194115266,
            -0.0658243448
          ],
          "DataType": 3
        }
      }
    ],
    "Outputs": [
      {
        "OutputType": 0,
        "OutputData": {
          "Values": [
            2.0
          ],
          "DataType": 0
        }
      }
    ]
  },
  {
    "Inputs": [
      {
        "InputType": 0,
        "InputData": {
          "Values": [
            -0.0717325658,
            0.128061861,
            0.161757544
          ],
          "DataType": 3
        }
      },
      {
        "InputType": 0,
        "InputData": {
          "Values": [
            0.004964374,
            0.212703258,
            -0.0687442049
          ],
          "DataType": 3
        }
      }
    ],
    "Outputs": [
      {
        "OutputType": 0,
        "OutputData": {
          "Values": [
            2.0
          ],
          "DataType": 0
        }
      }
    ]
  },
  {
    "Inputs": [
      {
        "InputType": 0,
        "InputData": {
          "Values": [
            -0.0717325658,
            0.128061861,
            0.161757544
          ],
          "DataType": 3
        }
      },
      {
        "InputType": 0,
        "InputData": {
          "Values": [
            -0.04213811,
            0.288450748,
            -0.0708596
          ],
          "DataType": 3
        }
      }
    ],
    "Outputs": [
      {
        "OutputType": 0,
        "OutputData": {
          "Values": [
            2.0
          ],
          "DataType": 0
        }
      }
    ]
  },
  {
    "Inputs": [
      {
        "InputType": 0,
        "InputData": {
          "Values": [
            -0.0717325658,
            0.128061861,
            0.161757544
          ],
          "DataType": 3
        }
      },
      {
        "InputType": 0,
        "InputData": {
          "Values": [
            -0.05363293,
            0.330674,
            -0.0713283941
          ],
          "DataType": 3
        }
      }
    ],
    "Outputs": [
      {
        "OutputType": 0,
        "OutputData": {
          "Values": [
            2.0
          ],
          "DataType": 0
        }
      }
    ]
  },
  {
    "Inputs": [
      {
        "InputType": 0,
        "InputData": {
          "Values": [
            -0.0717325658,
            0.128061861,
            0.161757544
          ],
          "DataType": 3
        }
      },
      {
        "InputType": 0,
        "InputData": {
          "Values": [
            -0.03948006,
            0.3263587,
            -0.0592648834
          ],
          "DataType": 3
        }
      }
    ],
    "Outputs": [
      {
        "OutputType": 0,
        "OutputData": {
          "Values": [
            2.0
          ],
          "DataType": 0
        }
      }
    ]
  },
  {
    "Inputs": [
      {
        "InputType": 0,
        "InputData": {
          "Values": [
            -0.0717325658,
            0.128061861,
            0.161757544
          ],
          "DataType": 3
        }
      },
      {
        "InputType": 0,
        "InputData": {
          "Values": [
            -0.0137597835,
            0.270382822,
            -0.04244431
          ],
          "DataType": 3
        }
      }
    ],
    "Outputs": [
      {
        "OutputType": 0,
        "OutputData": {
          "Values": [
            2.0
          ],
          "DataType": 0
        }
      }
    ]
  },
  {
    "Inputs": [
      {
        "InputType": 0,
        "InputData": {
          "Values": [
            -0.0717325658,
            0.128061861,
            0.161757544
          ],
          "DataType": 3
        }
      },
      {
        "InputType": 0,
        "InputData": {
          "Values": [
            -0.015393259,
            0.265280426,
            -0.04575404
          ],
          "DataType": 3
        }
      }
    ],
    "Outputs": [
      {
        "OutputType": 0,
        "OutputData": {
          "Values": [
            2.0
          ],
          "DataType": 0
        }
      }
    ]
  },
  {
    "Inputs": [
      {
        "InputType": 0,
        "InputData": {
          "Values": [
            -0.0717325658,
            0.128061861,
            0.161757544
          ],
          "DataType": 3
        }
      },
      {
        "InputType": 0,
        "InputData": {
          "Values": [
            -0.03177041,
            0.282018453,
            -0.0503712967
          ],
          "DataType": 3
        }
      }
    ],
    "Outputs": [
      {
        "OutputType": 0,
        "OutputData": {
          "Values": [
            2.0
          ],
          "DataType": 0
        }
      }
    ]
  },
  {
    "Inputs": [
      {
        "InputType": 0,
        "InputData": {
          "Values": [
            -0.0717325658,
            0.128061861,
            0.161757544
          ],
          "DataType": 3
        }
      },
      {
        "InputType": 0,
        "InputData": {
          "Values": [
            -0.0547471642,
            0.29873693,
            -0.06738247
          ],
          "DataType": 3
        }
      }
    ],
    "Outputs": [
      {
        "OutputType": 0,
        "OutputData": {
          "Values": [
            2.0
          ],
          "DataType": 0
        }
      }
    ]
  },
  {
    "Inputs": [
      {
        "InputType": 0,
        "InputData": {
          "Values": [
            -0.0717325658,
            0.128061861,
            0.161757544
          ],
          "DataType": 3
        }
      },
      {
        "InputType": 0,
        "InputData": {
          "Values": [
            -0.08621408,
            0.309641957,
            -0.09170576
          ],
          "DataType": 3
        }
      }
    ],
    "Outputs": [
      {
        "OutputType": 0,
        "OutputData": {
          "Values": [
            2.0
          ],
          "DataType": 0
        }
      }
    ]
  },
  {
    "Inputs": [
      {
        "InputType": 0,
        "InputData": {
          "Values": [
            -0.0717325658,
            0.128061861,
            0.161757544
          ],
          "DataType": 3
        }
      },
      {
        "InputType": 0,
        "InputData": {
          "Values": [
            -0.101221412,
            0.318496585,
            -0.110858873
          ],
          "DataType": 3
        }
      }
    ],
    "Outputs": [
      {
        "OutputType": 0,
        "OutputData": {
          "Values": [
            2.0
          ],
          "DataType": 0
        }
      }
    ]
  },
  {
    "Inputs": [
      {
        "InputType": 0,
        "InputData": {
          "Values": [
            -0.0717325658,
            0.128061861,
            0.161757544
          ],
          "DataType": 3
        }
      },
      {
        "InputType": 0,
        "InputData": {
          "Values": [
            -0.09698196,
            0.31371507,
            -0.1118174
          ],
          "DataType": 3
        }
      }
    ],
    "Outputs": [
      {
        "OutputType": 0,
        "OutputData": {
          "Values": [
            2.0
          ],
          "DataType": 0
        }
      }
    ]
  },
  {
    "Inputs": [
      {
        "InputType": 0,
        "InputData": {
          "Values": [
            -0.0717325658,
            0.128061861,
            0.161757544
          ],
          "DataType": 3
        }
      },
      {
        "InputType": 0,
        "InputData": {
          "Values": [
            -0.10140679,
            0.3152462,
            -0.11714875
          ],
          "DataType": 3
        }
      }
    ],
    "Outputs": [
      {
        "OutputType": 0,
        "OutputData": {
          "Values": [
            2.0
          ],
          "DataType": 0
        }
      }
    ]
  },
  {
    "Inputs": [
      {
        "InputType": 0,
        "InputData": {
          "Values": [
            -0.0717325658,
            0.128061861,
            0.161757544
          ],
          "DataType": 3
        }
      },
      {
        "InputType": 0,
        "InputData": {
          "Values": [
            -0.103383116,
            0.3069852,
            -0.117748879
          ],
          "DataType": 3
        }
      }
    ],
    "Outputs": [
      {
        "OutputType": 0,
        "OutputData": {
          "Values": [
            2.0
          ],
          "DataType": 0
        }
      }
    ]
  },
  {
    "Inputs": [
      {
        "InputType": 0,
        "InputData": {
          "Values": [
            -0.0717325658,
            0.128061861,
            0.161757544
          ],
          "DataType": 3
        }
      },
      {
        "InputType": 0,
        "InputData": {
          "Values": [
            -0.106214672,
            0.301534563,
            -0.11953181
          ],
          "DataType": 3
        }
      }
    ],
    "Outputs": [
      {
        "OutputType": 0,
        "OutputData": {
          "Values": [
            2.0
          ],
          "DataType": 0
        }
      }
    ]
  },
  {
    "Inputs": [
      {
        "InputType": 0,
        "InputData": {
          "Values": [
            -0.0717325658,
            0.128061861,
            0.161757544
          ],
          "DataType": 3
        }
      },
      {
        "InputType": 0,
        "InputData": {
          "Values": [
            -0.109939292,
            0.29538244,
            -0.119801052
          ],
          "DataType": 3
        }
      }
    ],
    "Outputs": [
      {
        "OutputType": 0,
        "OutputData": {
          "Values": [
            2.0
          ],
          "DataType": 0
        }
      }
    ]
  },
  {
    "Inputs": [
      {
        "InputType": 0,
        "InputData": {
          "Values": [
            -0.0717325658,
            0.128061861,
            0.161757544
          ],
          "DataType": 3
        }
      },
      {
        "InputType": 0,
        "InputData": {
          "Values": [
            -0.1137486,
            0.296045184,
            -0.121487595
          ],
          "DataType": 3
        }
      }
    ],
    "Outputs": [
      {
        "OutputType": 0,
        "OutputData": {
          "Values": [
            2.0
          ],
          "DataType": 0
        }
      }
    ]
  },
  {
    "Inputs": [
      {
        "InputType": 0,
        "InputData": {
          "Values": [
            -0.0717325658,
            0.128061861,
            0.161757544
          ],
          "DataType": 3
        }
      },
      {
        "InputType": 0,
        "InputData": {
          "Values": [
            -0.112399153,
            0.294785053,
            -0.120844461
          ],
          "DataType": 3
        }
      }
    ],
    "Outputs": [
      {
        "OutputType": 0,
        "OutputData": {
          "Values": [
            2.0
          ],
          "DataType": 0
        }
      }
    ]
  },
  {
    "Inputs": [
      {
        "InputType": 0,
        "InputData": {
          "Values": [
            -0.0717325658,
            0.128061861,
            0.161757544
          ],
          "DataType": 3
        }
      },
      {
        "InputType": 0,
        "InputData": {
          "Values": [
            -0.112803005,
            0.295166641,
            -0.120104358
          ],
          "DataType": 3
        }
      }
    ],
    "Outputs": [
      {
        "OutputType": 0,
        "OutputData": {
          "Values": [
            2.0
          ],
          "DataType": 0
        }
      }
    ]
  },
  {
    "Inputs": [
      {
        "InputType": 0,
        "InputData": {
          "Values": [
            -0.0717325658,
            0.128061861,
            0.161757544
          ],
          "DataType": 3
        }
      },
      {
        "InputType": 0,
        "InputData": {
          "Values": [
            -0.114082083,
            0.2952507,
            -0.118058369
          ],
          "DataType": 3
        }
      }
    ],
    "Outputs": [
      {
        "OutputType": 0,
        "OutputData": {
          "Values": [
            2.0
          ],
          "DataType": 0
        }
      }
    ]
  },
  {
    "Inputs": [
      {
        "InputType": 0,
        "InputData": {
          "Values": [
            -0.0717325658,
            0.128061861,
            0.161757544
          ],
          "DataType": 3
        }
      },
      {
        "InputType": 0,
        "InputData": {
          "Values": [
            -0.114792332,
            0.295310766,
            -0.117142022
          ],
          "DataType": 3
        }
      }
    ],
    "Outputs": [
      {
        "OutputType": 0,
        "OutputData": {
          "Values": [
            2.0
          ],
          "DataType": 0
        }
      }
    ]
  },
  {
    "Inputs": [
      {
        "InputType": 0,
        "InputData": {
          "Values": [
            -0.0717325658,
            0.128061861,
            0.161757544
          ],
          "DataType": 3
        }
      },
      {
        "InputType": 0,
        "InputData": {
          "Values": [
            -0.115082555,
            0.296442181,
            -0.116697095
          ],
          "DataType": 3
        }
      }
    ],
    "Outputs": [
      {
        "OutputType": 0,
        "OutputData": {
          "Values": [
            2.0
          ],
          "DataType": 0
        }
      }
    ]
  },
  {
    "Inputs": [
      {
        "InputType": 0,
        "InputData": {
          "Values": [
            -0.0717325658,
            0.128061861,
            0.161757544
          ],
          "DataType": 3
        }
      },
      {
        "InputType": 0,
        "InputData": {
          "Values": [
            -0.115063481,
            0.29673776,
            -0.116480745
          ],
          "DataType": 3
        }
      }
    ],
    "Outputs": [
      {
        "OutputType": 0,
        "OutputData": {
          "Values": [
            2.0
          ],
          "DataType": 0
        }
      }
    ]
  },
  {
    "Inputs": [
      {
        "InputType": 0,
        "InputData": {
          "Values": [
            -0.0717325658,
            0.128061861,
            0.161757544
          ],
          "DataType": 3
        }
      },
      {
        "InputType": 0,
        "InputData": {
          "Values": [
            -0.115058668,
            0.2962633,
            -0.114951186
          ],
          "DataType": 3
        }
      }
    ],
    "Outputs": [
      {
        "OutputType": 0,
        "OutputData": {
          "Values": [
            2.0
          ],
          "DataType": 0
        }
      }
    ]
  },
  {
    "Inputs": [
      {
        "InputType": 0,
        "InputData": {
          "Values": [
            -0.0717325658,
            0.128061861,
            0.161757544
          ],
          "DataType": 3
        }
      },
      {
        "InputType": 0,
        "InputData": {
          "Values": [
            -0.117487609,
            0.298198,
            -0.113700233
          ],
          "DataType": 3
        }
      }
    ],
    "Outputs": [
      {
        "OutputType": 0,
        "OutputData": {
          "Values": [
            2.0
          ],
          "DataType": 0
        }
      }
    ]
  },
  {
    "Inputs": [
      {
        "InputType": 0,
        "InputData": {
          "Values": [
            -0.0717325658,
            0.128061861,
            0.161757544
          ],
          "DataType": 3
        }
      },
      {
        "InputType": 0,
        "InputData": {
          "Values": [
            -0.118316211,
            0.298276961,
            -0.113551348
          ],
          "DataType": 3
        }
      }
    ],
    "Outputs": [
      {
        "OutputType": 0,
        "OutputData": {
          "Values": [
            2.0
          ],
          "DataType": 0
        }
      }
    ]
  },
  {
    "Inputs": [
      {
        "InputType": 0,
        "InputData": {
          "Values": [
            -0.0717325658,
            0.128061861,
            0.161757544
          ],
          "DataType": 3
        }
      },
      {
        "InputType": 0,
        "InputData": {
          "Values": [
            -0.117772229,
            0.297572643,
            -0.113004163
          ],
          "DataType": 3
        }
      }
    ],
    "Outputs": [
      {
        "OutputType": 0,
        "OutputData": {
          "Values": [
            2.0
          ],
          "DataType": 0
        }
      }
    ]
  },
  {
    "Inputs": [
      {
        "InputType": 0,
        "InputData": {
          "Values": [
            -0.0717325658,
            0.128061861,
            0.161757544
          ],
          "DataType": 3
        }
      },
      {
        "InputType": 0,
        "InputData": {
          "Values": [
            -0.118037969,
            0.298869431,
            -0.113280259
          ],
          "DataType": 3
        }
      }
    ],
    "Outputs": [
      {
        "OutputType": 0,
        "OutputData": {
          "Values": [
            2.0
          ],
          "DataType": 0
        }
      }
    ]
  },
  {
    "Inputs": [
      {
        "InputType": 0,
        "InputData": {
          "Values": [
            -0.0717325658,
            0.128061861,
            0.161757544
          ],
          "DataType": 3
        }
      },
      {
        "InputType": 0,
        "InputData": {
          "Values": [
            -0.09781067,
            0.2848791,
            -0.114023216
          ],
          "DataType": 3
        }
      }
    ],
    "Outputs": [
      {
        "OutputType": 0,
        "OutputData": {
          "Values": [
            2.0
          ],
          "DataType": 0
        }
      }
    ]
  },
  {
    "Inputs": [
      {
        "InputType": 0,
        "InputData": {
          "Values": [
            -0.0717325658,
            0.128061861,
            0.161757544
          ],
          "DataType": 3
        }
      },
      {
        "InputType": 0,
        "InputData": {
          "Values": [
            -0.00781150861,
            0.1756734,
            -0.135419682
          ],
          "DataType": 3
        }
      }
    ],
    "Outputs": [
      {
        "OutputType": 0,
        "OutputData": {
          "Values": [
            2.0
          ],
          "DataType": 0
        }
      }
    ]
  },
  {
    "Inputs": [
      {
        "InputType": 0,
        "InputData": {
          "Values": [
            -0.0717325658,
            0.128061861,
            0.161757544
          ],
          "DataType": 3
        }
      },
      {
        "InputType": 0,
        "InputData": {
          "Values": [
            0.02217313,
            0.08070263,
            -0.146279946
          ],
          "DataType": 3
        }
      }
    ],
    "Outputs": [
      {
        "OutputType": 0,
        "OutputData": {
          "Values": [
            2.0
          ],
          "DataType": 0
        }
      }
    ]
  },
  {
    "Inputs": [
      {
        "InputType": 0,
        "InputData": {
          "Values": [
            -0.0717325658,
            0.128061861,
            0.161757544
          ],
          "DataType": 3
        }
      },
      {
        "InputType": 0,
        "InputData": {
          "Values": [
            0.0740545839,
            0.0770662352,
            -0.208428055
          ],
          "DataType": 3
        }
      }
    ],
    "Outputs": [
      {
        "OutputType": 0,
        "OutputData": {
          "Values": [
            2.0
          ],
          "DataType": 0
        }
      }
    ]
  },
  {
    "Inputs": [
      {
        "InputType": 0,
        "InputData": {
          "Values": [
            -0.0717325658,
            0.128061861,
            0.161757544
          ],
          "DataType": 3
        }
      },
      {
        "InputType": 0,
        "InputData": {
          "Values": [
            0.0740545839,
            0.0770662352,
            -0.208428055
          ],
          "DataType": 3
        }
      }
    ],
    "Outputs": [
      {
        "OutputType": 0,
        "OutputData": {
          "Values": [
            2.0
          ],
          "DataType": 0
        }
      }
    ]
  }
]